_prox_tv.abi3.so
.libs_prox_tv/liblapack-78e59728.so.3.0.3
.libs_prox_tv/libgomp-3300acd3.so.1.0.0
.libs_prox_tv/libgfortran-bfa58d52.so.1.0.0
.libs_prox_tv/libblas-2d5b9174.so.3.0.3
prox_tv/prox_tv_build.py
prox_tv/__init__.py
prox_tv/prox_tv_test.py
prox_tv-3.3.0.dist-info/WHEEL
prox_tv-3.3.0.dist-info/top_level.txt
prox_tv-3.3.0.dist-info/METADATA
prox_tv-3.3.0.dist-info/RECORD
